sql_connectors/__init__.py
sql_connectors/_version.py
sql_connectors/client.py
sql_connectors/config.py
sql_connectors/config_util.py
sql_connectors/connections.py
sql_connectors/exceptions.py
sql_connectors/storage.py
sql_connectors/util.py
sql_connectors-1.0.2.dist-info/AUTHORS.rst
sql_connectors-1.0.2.dist-info/LICENSE
sql_connectors-1.0.2.dist-info/METADATA
sql_connectors-1.0.2.dist-info/WHEEL
sql_connectors-1.0.2.dist-info/top_level.txt
sql_connectors-1.0.2.dist-info/RECORD
