Metadata-Version: 2.1
Name: sql-connectors
Version: 1.0.2
Summary: A simple wrapper for SQL connections using SQLAlchemy and Pandas read_sql to standardize SQL workflow.
Home-page: https://github.com/aiguofer/sql_connectors
Author: Diego Fernandez
Author-email: aiguo.fernandez@gmail.com
License: MIT license
Keywords: sql_connectors
Platform: UNKNOWN
Classifier: Development Status :: 2 - Pre-Alpha
Classifier: Intended Audience :: Developers
Classifier: License :: OSI Approved :: MIT License
Classifier: Natural Language :: English
Classifier: Programming Language :: Python :: 2
Classifier: Programming Language :: Python :: 2.7
Classifier: Programming Language :: Python :: 3
Classifier: Programming Language :: Python :: 3.4
Classifier: Programming Language :: Python :: 3.5
Classifier: Programming Language :: Python :: 3.6
Provides-Extra: dev
